spice_segmenter/__init__.py
spice_segmenter/constraint_solver.py
spice_segmenter/coordinates.py
spice_segmenter/decorators.py
spice_segmenter/events.py
spice_segmenter/occultation.py
spice_segmenter/ops.py
spice_segmenter/py.typed
spice_segmenter/quick.py
spice_segmenter/search_reporter.py
spice_segmenter/spice_window.py
spice_segmenter/surface.py
spice_segmenter/trajectory_properties.py
spice_segmenter/types.py
spice_segmenter/utils.py
spice_segmenter/visibility.py
spice_segmenter-0.0.5.dist-info/LICENCE
spice_segmenter-0.0.5.dist-info/LICENSE
spice_segmenter-0.0.5.dist-info/METADATA
spice_segmenter-0.0.5.dist-info/WHEEL
spice_segmenter-0.0.5.dist-info/RECORD
