Metadata-Version: 2.1
Name: spice-segmenter
Version: 0.0.5
Summary: Spice-based segmenter, wrapping event finding routines within spice toolkit.
Home-page: https://luca-penasa.github.io/spice-segmenter
License: MIT
Author: Luca Penasa
Author-email: luca.penasa@gmail.com
Requires-Python: >=3.10,<4.0
Classifier: Development Status :: 4 - Beta
Classifier: Intended Audience :: Developers
Classifier: License :: OSI Approved :: MIT License
Classifier: Operating System :: OS Independent
Classifier: Programming Language :: Python
Classifier: Programming Language :: Python :: 3
Classifier: Programming Language :: Python :: 3.10
Classifier: Programming Language :: Python :: 3.11
Classifier: Programming Language :: Python :: 3.12
Classifier: Topic :: Software Development :: Libraries :: Python Modules
Classifier: Typing :: Typed
Requires-Dist: anytree (>=2.8.0,<3.0.0)
Requires-Dist: attrs (>20.0.0)
Requires-Dist: datetimerange (>=2.1.0,<3.0.0)
Requires-Dist: importlib-metadata (>=8.5.0,<9.0.0)
Requires-Dist: loguru (>=0.7.2,<0.8.0)
Requires-Dist: pandas (>=2.0.1,<3.0.0)
Requires-Dist: pint (>=0.20)
Requires-Dist: planetary-coverage (>=1.0.0)
Requires-Dist: quick-spice-manager (>=0.0.1,<0.0.2)
Requires-Dist: spiceypy (>=5.1.1)
Requires-Dist: tqdm (>=4.65.0,<5.0.0)
Project-URL: Documentation, https://luca-penasa.github.io/spice-segmenter
Project-URL: Repository, https://github.com/luca-penasa/spice-segmenter
